{
	"asset": {
		"version": "1.0"
	},
	"geometricError": 4.330127018922193,
	"root": {
		"children": [
			{
				"content": {
					"uri": "0/tileset.json"
				},
				"boundingVolume": {
					"region": [
						0.08316883692345851,
						0.9129861257277324,
						0.08319129954622326,
						0.9129935163192073,
						20.99,
						25.595
					]
				},
				"geometricError": 2.1650635094610964,
				"refine": "ADD"
			}
		],
		"content": {
			"uri": "content.pnts"
		},
		"boundingVolume": {
			"region": [
				0.08316883692345851,
				0.9129861257277324,
				0.08321376216898797,
				0.9130009068396291,
				20.99,
				30.2
			]
		},
		"geometricError": 4.330127018922193,
		"refine": "ADD"
	}
}