{
	"asset": {
		"version": "1.0"
	},
	"geometricError": 0.5412658773652741,
	"root": {
		"children": [
			{
				"content": {
					"uri": "0/content.pnts"
				},
				"boundingVolume": {
					"region": [
						0.08330922831573805,
						0.9129879733822623,
						0.08331203614358364,
						0.912988897207862,
						10.62875,
						11.204374999999999
					]
				},
				"geometricError": 0.27063293868263705,
				"refine": "ADD"
			},
			{
				"content": {
					"uri": "1/content.pnts"
				},
				"boundingVolume": {
					"region": [
						0.08331203614358364,
						0.9129879733822623,
						0.08331484397142923,
						0.912988897207862,
						10.62875,
						11.204374999999999
					]
				},
				"geometricError": 0.27063293868263705,
				"refine": "ADD"
			},
			{
				"content": {
					"uri": "2/content.pnts"
				},
				"boundingVolume": {
					"region": [
						0.08330922831573805,
						0.912988897207862,
						0.08331203614358364,
						0.9129898210323515,
						10.62875,
						11.204374999999999
					]
				},
				"geometricError": 0.27063293868263705,
				"refine": "ADD"
			},
			{
				"content": {
					"uri": "3/content.pnts"
				},
				"boundingVolume": {
					"region": [
						0.08331203614358364,
						0.912988897207862,
						0.08331484397142923,
						0.9129898210323515,
						10.62875,
						11.204374999999999
					]
				},
				"geometricError": 0.27063293868263705,
				"refine": "ADD"
			}
		],
		"content": {
			"uri": "content.pnts"
		},
		"boundingVolume": {
			"region": [
				0.08330922831573805,
				0.9129879733822623,
				0.08331484397142923,
				0.9129898210323515,
				10.62875,
				11.78
			]
		},
		"geometricError": 0.5412658773652741,
		"refine": "ADD"
	}
}