{
  "geometricError": 2000.0,
  "root": {
    "children": [
      {
        "children": [
          {
            "children": [
              {
                "geometricError": 0.0,
                "boundingVolume": {
                  "region": [
                    0.09061403264522681,
                    0.9077485021054028,
                    0.09086362530976669,
                    0.9079080458531799,
                    43.39457554426359,
                    76.34470617543066
                  ]
                },
                "content": {
                  "uri": "content/2_0_0_3.glb"
                }
              }
            ],
            "geometricError": 1.0,
            "boundingVolume": {
              "region": [
                0.09061403264522681,
                0.9077485021054028,
                0.09086362530976669,
                0.9079080458531799,
                43.39457554426359,
                76.34470617543066
              ]
            },
            "content": {
              "uri": "content/2_0_0_2.glb"
            }
          }
        ],
        "geometricError": 5.0,
        "boundingVolume": {
          "region": [
            0.09061403264522681,
            0.9077485021054028,
            0.09086362530976669,
            0.9079080458531799,
            43.39457554426359,
            76.34470617543066
          ]
        },
        "content": {
          "uri": "content/2_0_0_1.glb"
        }
      },
      {
        "children": [
          {
            "children": [
              {
                "geometricError": 0.0,
                "boundingVolume": {
                  "region": [
                    0.09061298305466546,
                    0.9079054920537605,
                    0.09072300907362603,
                    0.9079866440366778,
                    43.39457554426359,
                    76.34470617543066
                  ]
                },
                "content": {
                  "uri": "content/3_0_2_3.glb"
                }
              }
            ],
            "geometricError": 1.0,
            "boundingVolume": {
              "region": [
                0.09061298305466546,
                0.9079054920537605,
                0.09072300907362603,
                0.9079866440366778,
                43.39457554426359,
                76.34470617543066
              ]
            },
            "content": {
              "uri": "content/3_0_2_2.glb"
            }
          }
        ],
        "geometricError": 5.0,
        "boundingVolume": {
          "region": [
            0.09061298305466546,
            0.9079054920537605,
            0.09072300907362603,
            0.9079866440366778,
            43.39457554426359,
            76.34470617543066
          ]
        },
        "content": {
          "uri": "content/3_0_2_1.glb"
        }
      },
      {
        "children": [
          {
            "children": [
              {
                "geometricError": 0.0,
                "boundingVolume": {
                  "region": [
                    0.09061434670331876,
                    0.9079842541689237,
                    0.09068844564659861,
                    0.9080423520902483,
                    43.39457554426359,
                    76.34470617543066
                  ]
                },
                "content": {
                  "uri": "content/3_0_3_3.glb"
                }
              }
            ],
            "geometricError": 1.0,
            "boundingVolume": {
              "region": [
                0.09061434670331876,
                0.9079842541689237,
                0.09068844564659861,
                0.9080423520902483,
                43.39457554426359,
                76.34470617543066
              ]
            },
            "content": {
              "uri": "content/3_0_3_2.glb"
            }
          }
        ],
        "geometricError": 5.0,
        "boundingVolume": {
          "region": [
            0.09061434670331876,
            0.9079842541689237,
            0.09068844564659861,
            0.9080423520902483,
            43.39457554426359,
            76.34470617543066
          ]
        },
        "content": {
          "uri": "content/3_0_3_1.glb"
        }
      },
      {
        "children": [
          {
            "children": [
              {
                "geometricError": 0.0,
                "boundingVolume": {
                  "region": [
                    0.09081129013301964,
                    0.9079920277784153,
                    0.0908307647050821,
                    0.9080102689839463,
                    43.39457554426359,
                    76.34470617543066
                  ]
                },
                "content": {
                  "uri": "content/3_1_3_3.glb"
                }
              }
            ],
            "geometricError": 1.0,
            "boundingVolume": {
              "region": [
                0.09081129013301964,
                0.9079920277784153,
                0.0908307647050821,
                0.9080102689839463,
                43.39457554426359,
                76.34470617543066
              ]
            },
            "content": {
              "uri": "content/3_1_3_2.glb"
            }
          }
        ],
        "geometricError": 5.0,
        "boundingVolume": {
          "region": [
            0.09081129013301964,
            0.9079920277784153,
            0.0908307647050821,
            0.9080102689839463,
            43.39457554426359,
            76.34470617543066
          ]
        },
        "content": {
          "uri": "content/3_1_3_1.glb"
        }
      },
      {
        "children": [
          {
            "children": [
              {
                "geometricError": 0.0,
                "boundingVolume": {
                  "region": [
                    0.09090269161051438,
                    0.9077615924460559,
                    0.09099103694752758,
                    0.9079024673641484,
                    43.39457554426359,
                    76.34470617543066
                  ]
                },
                "content": {
                  "uri": "content/2_1_0_3.glb"
                }
              }
            ],
            "geometricError": 1.0,
            "boundingVolume": {
              "region": [
                0.09090269161051438,
                0.9077615924460559,
                0.09099103694752758,
                0.9079024673641484,
                43.39457554426359,
                76.34470617543066
              ]
            },
            "content": {
              "uri": "content/2_1_0_2.glb"
            }
          }
        ],
        "geometricError": 5.0,
        "boundingVolume": {
          "region": [
            0.09090269161051438,
            0.9077615924460559,
            0.09099103694752758,
            0.9079024673641484,
            43.39457554426359,
            76.34470617543066
          ]
        },
        "content": {
          "uri": "content/2_1_0_1.glb"
        }
      },
      {
        "children": [
          {
            "children": [
              {
                "geometricError": 0.0,
                "boundingVolume": {
                  "region": [
                    0.09085920655141594,
                    0.9079039713960392,
                    0.09110897425526603,
                    0.9080319927026289,
                    43.39457554426359,
                    76.34470617543066
                  ]
                },
                "content": {
                  "uri": "content/2_1_1_3.glb"
                }
              }
            ],
            "geometricError": 1.0,
            "boundingVolume": {
              "region": [
                0.09085920655141594,
                0.9079039713960392,
                0.09110897425526603,
                0.9080319927026289,
                43.39457554426359,
                76.34470617543066
              ]
            },
            "content": {
              "uri": "content/2_1_1_2.glb"
            }
          }
        ],
        "geometricError": 5.0,
        "boundingVolume": {
          "region": [
            0.09085920655141594,
            0.9079039713960392,
            0.09110897425526603,
            0.9080319927026289,
            43.39457554426359,
            76.34470617543066
          ]
        },
        "content": {
          "uri": "content/2_1_1_1.glb"
        }
      },
      {
        "children": [
          {
            "children": [
              {
                "geometricError": 0.0,
                "boundingVolume": {
                  "region": [
                    0.0906132308908071,
                    0.9080945750287797,
                    0.09112292486072501,
                    0.9083790221717264,
                    43.39457554426359,
                    76.34470617543066
                  ]
                },
                "content": {
                  "uri": "content/1_0_1_3.glb"
                }
              }
            ],
            "geometricError": 1.0,
            "boundingVolume": {
              "region": [
                0.0906132308908071,
                0.9080945750287797,
                0.09112292486072501,
                0.9083790221717264,
                43.39457554426359,
                76.34470617543066
              ]
            },
            "content": {
              "uri": "content/1_0_1_2.glb"
            }
          }
        ],
        "geometricError": 5.0,
        "boundingVolume": {
          "region": [
            0.0906132308908071,
            0.9080945750287797,
            0.09112292486072501,
            0.9083790221717264,
            43.39457554426359,
            76.34470617543066
          ]
        },
        "content": {
          "uri": "content/1_0_1_1.glb"
        }
      },
      {
        "children": [
          {
            "children": [
              {
                "geometricError": 0.0,
                "boundingVolume": {
                  "region": [
                    0.09133581725127249,
                    0.9078542277930248,
                    0.09137926302847363,
                    0.9078908996664862,
                    43.39457554426359,
                    76.34470617543066
                  ]
                },
                "content": {
                  "uri": "content/2_2_0_3.glb"
                }
              }
            ],
            "geometricError": 1.0,
            "boundingVolume": {
              "region": [
                0.09133581725127249,
                0.9078542277930248,
                0.09137926302847363,
                0.9078908996664862,
                43.39457554426359,
                76.34470617543066
              ]
            },
            "content": {
              "uri": "content/2_2_0_2.glb"
            }
          }
        ],
        "geometricError": 5.0,
        "boundingVolume": {
          "region": [
            0.09133581725127249,
            0.9078542277930248,
            0.09137926302847363,
            0.9078908996664862,
            43.39457554426359,
            76.34470617543066
          ]
        },
        "content": {
          "uri": "content/2_2_0_1.glb"
        }
      },
      {
        "children": [
          {
            "children": [
              {
                "geometricError": 0.0,
                "boundingVolume": {
                  "region": [
                    0.09115549838962457,
                    0.9079178962231264,
                    0.09136569750459264,
                    0.9080647483665829,
                    43.39457554426359,
                    76.34470617543066
                  ]
                },
                "content": {
                  "uri": "content/2_2_1_3.glb"
                }
              }
            ],
            "geometricError": 1.0,
            "boundingVolume": {
              "region": [
                0.09115549838962457,
                0.9079178962231264,
                0.09136569750459264,
                0.9080647483665829,
                43.39457554426359,
                76.34470617543066
              ]
            },
            "content": {
              "uri": "content/2_2_1_2.glb"
            }
          }
        ],
        "geometricError": 5.0,
        "boundingVolume": {
          "region": [
            0.09115549838962457,
            0.9079178962231264,
            0.09136569750459264,
            0.9080647483665829,
            43.39457554426359,
            76.34470617543066
          ]
        },
        "content": {
          "uri": "content/2_2_1_1.glb"
        }
      },
      {
        "children": [
          {
            "children": [
              {
                "geometricError": 0.0,
                "boundingVolume": {
                  "region": [
                    0.09137723424681604,
                    0.9077591870337062,
                    0.09163167464746588,
                    0.907908071287243,
                    43.39457554426359,
                    76.34470617543066
                  ]
                },
                "content": {
                  "uri": "content/2_3_0_3.glb"
                }
              }
            ],
            "geometricError": 1.0,
            "boundingVolume": {
              "region": [
                0.09137723424681604,
                0.9077591870337062,
                0.09163167464746588,
                0.907908071287243,
                43.39457554426359,
                76.34470617543066
              ]
            },
            "content": {
              "uri": "content/2_3_0_2.glb"
            }
          }
        ],
        "geometricError": 5.0,
        "boundingVolume": {
          "region": [
            0.09137723424681604,
            0.9077591870337062,
            0.09163167464746588,
            0.907908071287243,
            43.39457554426359,
            76.34470617543066
          ]
        },
        "content": {
          "uri": "content/2_3_0_1.glb"
        }
      },
      {
        "children": [
          {
            "children": [
              {
                "geometricError": 0.0,
                "boundingVolume": {
                  "region": [
                    0.09143107072888167,
                    0.9079090890084157,
                    0.09150667108715835,
                    0.9079854581652901,
                    43.39457554426359,
                    76.34470617543066
                  ]
                },
                "content": {
                  "uri": "content/3_6_2_3.glb"
                }
              }
            ],
            "geometricError": 1.0,
            "boundingVolume": {
              "region": [
                0.09143107072888167,
                0.9079090890084157,
                0.09150667108715835,
                0.9079854581652901,
                43.39457554426359,
                76.34470617543066
              ]
            },
            "content": {
              "uri": "content/3_6_2_2.glb"
            }
          }
        ],
        "geometricError": 5.0,
        "boundingVolume": {
          "region": [
            0.09143107072888167,
            0.9079090890084157,
            0.09150667108715835,
            0.9079854581652901,
            43.39457554426359,
            76.34470617543066
          ]
        },
        "content": {
          "uri": "content/3_6_2_1.glb"
        }
      },
      {
        "children": [
          {
            "children": [
              {
                "geometricError": 0.0,
                "boundingVolume": {
                  "region": [
                    0.09139511381948852,
                    0.9079841920510597,
                    0.0915067932883278,
                    0.908063551449927,
                    43.39457554426359,
                    76.34470617543066
                  ]
                },
                "content": {
                  "uri": "content/3_6_3_3.glb"
                }
              }
            ],
            "geometricError": 1.0,
            "boundingVolume": {
              "region": [
                0.09139511381948852,
                0.9079841920510597,
                0.0915067932883278,
                0.908063551449927,
                43.39457554426359,
                76.34470617543066
              ]
            },
            "content": {
              "uri": "content/3_6_3_2.glb"
            }
          }
        ],
        "geometricError": 5.0,
        "boundingVolume": {
          "region": [
            0.09139511381948852,
            0.9079841920510597,
            0.0915067932883278,
            0.908063551449927,
            43.39457554426359,
            76.34470617543066
          ]
        },
        "content": {
          "uri": "content/3_6_3_1.glb"
        }
      },
      {
        "children": [
          {
            "children": [
              {
                "geometricError": 0.0,
                "boundingVolume": {
                  "region": [
                    0.09150267777631305,
                    0.90790798983593,
                    0.0915851441813949,
                    0.907986327590645,
                    43.39457554426359,
                    76.34470617543066
                  ]
                },
                "content": {
                  "uri": "content/3_7_2_3.glb"
                }
              }
            ],
            "geometricError": 1.0,
            "boundingVolume": {
              "region": [
                0.09150267777631305,
                0.90790798983593,
                0.0915851441813949,
                0.907986327590645,
                43.39457554426359,
                76.34470617543066
              ]
            },
            "content": {
              "uri": "content/3_7_2_2.glb"
            }
          }
        ],
        "geometricError": 5.0,
        "boundingVolume": {
          "region": [
            0.09150267777631305,
            0.90790798983593,
            0.0915851441813949,
            0.907986327590645,
            43.39457554426359,
            76.34470617543066
          ]
        },
        "content": {
          "uri": "content/3_7_2_1.glb"
        }
      },
      {
        "children": [
          {
            "children": [
              {
                "geometricError": 0.0,
                "boundingVolume": {
                  "region": [
                    0.09150336894806309,
                    0.9079841898466542,
                    0.091632642882982,
                    0.90804277508765,
                    43.39457554426359,
                    76.34470617543066
                  ]
                },
                "content": {
                  "uri": "content/3_7_3_3.glb"
                }
              }
            ],
            "geometricError": 1.0,
            "boundingVolume": {
              "region": [
                0.09150336894806309,
                0.9079841898466542,
                0.091632642882982,
                0.90804277508765,
                43.39457554426359,
                76.34470617543066
              ]
            },
            "content": {
              "uri": "content/3_7_3_2.glb"
            }
          }
        ],
        "geometricError": 5.0,
        "boundingVolume": {
          "region": [
            0.09150336894806309,
            0.9079841898466542,
            0.091632642882982,
            0.90804277508765,
            43.39457554426359,
            76.34470617543066
          ]
        },
        "content": {
          "uri": "content/3_7_3_1.glb"
        }
      },
      {
        "children": [
          {
            "children": [
              {
                "geometricError": 0.0,
                "boundingVolume": {
                  "region": [
                    0.09113538365871472,
                    0.9080638730934355,
                    0.09163008591547289,
                    0.9083792307899299,
                    43.39457554426359,
                    76.34470617543066
                  ]
                },
                "content": {
                  "uri": "content/1_1_1_3.glb"
                }
              }
            ],
            "geometricError": 1.0,
            "boundingVolume": {
              "region": [
                0.09113538365871472,
                0.9080638730934355,
                0.09163008591547289,
                0.9083792307899299,
                43.39457554426359,
                76.34470617543066
              ]
            },
            "content": {
              "uri": "content/1_1_1_2.glb"
            }
          }
        ],
        "geometricError": 5.0,
        "boundingVolume": {
          "region": [
            0.09113538365871472,
            0.9080638730934355,
            0.09163008591547289,
            0.9083792307899299,
            43.39457554426359,
            76.34470617543066
          ]
        },
        "content": {
          "uri": "content/1_1_1_1.glb"
        }
      }
    ],
    "transform": [
      1.0,
      0.0,
      0.0,
      0.0,
      0.0,
      1.0,
      0.0,
      0.0,
      0.0,
      0.0,
      1.0,
      0.0,
      3916170.0,
      357843.40625,
      5004736.5,
      1.0
    ],
    "geometricError": 2000.0,
    "refine": "REPLACE",
    "boundingVolume": {
      "region": [
        0.09061296560137294,
        0.9077484846521103,
        0.09163266033627453,
        0.9083792482432224,
        43.39457554426359,
        76.34470617543066
      ]
    }
  },
  "asset": {
    "generator": "pg2b3dm 2.6.0.0",
    "version": "1.1"
  }
}