{
	"asset": {
		"version": "1.0"
	},
	"geometricError": 1.0825317547305482,
	"root": {
		"children": [
			{
				"content": {
					"uri": "0/content.pnts"
				},
				"boundingVolume": {
					"region": [
						0.0832639185039456,
						0.9129353271238193,
						0.08326953333904555,
						0.9129371746064245,
						7.57,
						8.721250000000001
					]
				},
				"geometricError": 0.5412658773652741,
				"refine": "ADD"
			},
			{
				"content": {
					"uri": "1/tileset.json"
				},
				"boundingVolume": {
					"region": [
						0.08326953333904555,
						0.9129353271238193,
						0.08327514817414551,
						0.9129371746064245,
						7.57,
						8.721250000000001
					]
				},
				"geometricError": 0.5412658773652741,
				"refine": "ADD"
			}
		],
		"content": {
			"uri": "content.pnts"
		},
		"boundingVolume": {
			"region": [
				0.0832639185039456,
				0.9129353271238193,
				0.08327514817414551,
				0.9129390220845904,
				7.57,
				9.8725
			]
		},
		"geometricError": 1.0825317547305482,
		"refine": "ADD"
	}
}