{
	"asset": {
		"version": "1.0"
	},
	"geometricError": 1.0825317547305482,
	"root": {
		"children": [
			{
				"content": {
					"uri": "0/tileset.json"
				},
				"boundingVolume": {
					"region": [
						0.08324145916354572,
						0.9129611914762991,
						0.0832470739986457,
						0.9129630388967515,
						7.57,
						8.721250000000001
					]
				},
				"geometricError": 0.5412658773652741,
				"refine": "ADD"
			},
			{
				"content": {
					"uri": "1/tileset.json"
				},
				"boundingVolume": {
					"region": [
						0.0832470739986457,
						0.9129611914762991,
						0.08325268883374566,
						0.9129630388967515,
						7.57,
						8.721250000000001
					]
				},
				"geometricError": 0.5412658773652741,
				"refine": "ADD"
			},
			{
				"content": {
					"uri": "2/tileset.json"
				},
				"boundingVolume": {
					"region": [
						0.08324145916354572,
						0.9129630388967515,
						0.0832470739986457,
						0.9129648863127644,
						7.57,
						8.721250000000001
					]
				},
				"geometricError": 0.5412658773652741,
				"refine": "ADD"
			},
			{
				"content": {
					"uri": "3/tileset.json"
				},
				"boundingVolume": {
					"region": [
						0.0832470739986457,
						0.9129630388967515,
						0.08325268883374566,
						0.9129648863127644,
						7.57,
						8.721250000000001
					]
				},
				"geometricError": 0.5412658773652741,
				"refine": "ADD"
			},
			{
				"content": {
					"uri": "4/content.pnts"
				},
				"boundingVolume": {
					"region": [
						0.08324145916354572,
						0.9129611914762991,
						0.0832470739986457,
						0.9129630388967515,
						8.721250000000001,
						9.8725
					]
				},
				"geometricError": 0.5412658773652741,
				"refine": "ADD"
			},
			{
				"content": {
					"uri": "5/tileset.json"
				},
				"boundingVolume": {
					"region": [
						0.0832470739986457,
						0.9129611914762991,
						0.08325268883374566,
						0.9129630388967515,
						8.721250000000001,
						9.8725
					]
				},
				"geometricError": 0.5412658773652741,
				"refine": "ADD"
			},
			{
				"content": {
					"uri": "6/content.pnts"
				},
				"boundingVolume": {
					"region": [
						0.08324145916354572,
						0.9129630388967515,
						0.0832470739986457,
						0.9129648863127644,
						8.721250000000001,
						9.8725
					]
				},
				"geometricError": 0.5412658773652741,
				"refine": "ADD"
			},
			{
				"content": {
					"uri": "7/tileset.json"
				},
				"boundingVolume": {
					"region": [
						0.0832470739986457,
						0.9129630388967515,
						0.08325268883374566,
						0.9129648863127644,
						8.721250000000001,
						9.8725
					]
				},
				"geometricError": 0.5412658773652741,
				"refine": "ADD"
			}
		],
		"content": {
			"uri": "content.pnts"
		},
		"boundingVolume": {
			"region": [
				0.08324145916354572,
				0.9129611914762991,
				0.08325268883374566,
				0.9129648863127644,
				7.57,
				9.8725
			]
		},
		"geometricError": 1.0825317547305482,
		"refine": "ADD"
	}
}